Workbook

Sheet 问题清单
A1: 序号 | B1: 问题 | C1: 描述 | D1: 违反条例 | E1: 证据
A2: 1 | B2: ='1.内部控制管理方面'!A5 -> 问题摘要：内部控制体系文件不完整 | C2: ='1.内部控制管理方面'!A6 -> 1.内部控制体系文件不完整，未及时更新。发展研究中心内部控制手册尚处于修订完善阶段，未能提供最新完整、统一、现行有效的内部控制手册，不利于全面核查内控流程、岗位职责、风险防控等体系建设及执行情况，内部控制资料支撑不足。 2.内部控制制度体系不健全，制度缺失。 现有内控制度不完整，单位层面未建立内部控制风险评估、内部控制体系监督评价相关制度；业务层面缺少差旅费、会议费、会务卡管理等制度，内控覆盖不全面，难以有效开展风险防控、监督评价及经费规范管理。 | D2: ='1.内部控制管理方面'!A12 -> 不符合《行政事业单位内部控制规范》第七条 “单位应当根据本规范建立适合本单位实际情况的内部控制体系，并组织实施。具体工作包括梳理单位各类经济活动的业务流程，明确业务环节，系统分析经济活动风险，确定风险点，选择风险应对策略，在此基础上根据国家有关规定建立健全单位各项内部管理制度并督促相关工作人员认真执行”的规定。 | E2: ='1.内部控制管理方面'!A8 -> 《北京市市场监管发展研究中心财务制度汇编》
A3: 2 | B3: ='2.预算编报方面'!A5 -> 问题摘要：政府采购预算编报不准确，导致预算执行率低 | C3: ='2.预算编报方面'!A6 -> 发展研究中心“系统干部培训经费”编报不严谨，预算编报以“全员在外550元”为标准编制，但实际执行过程中未按照该标准落实，编报依据与实际执行情况脱节，导致政府采购预算实际执行率较低，2023年、2024年、2025年政府采购预算执行率分别为39.85%、13.08%、31%。 | D3: ='2.预算编报方面'!A12 -> 不符合《事业单位财务规则》第十一条“事业单位应当严格执行批准的预算。预算执行中，国家对财政补助收入和财政专户管理资金的预算一般不予调剂，确需调剂的，由事业单位报主管部门审核后报财政部门调剂；其他资金确需调剂的，按照国家有关规定办理”的规定。 | E3: ='2.预算编报方面'!A8 -> 2023年、2024年、2025年决算报表。
A4: 3 | B4: ='3.采购管理'!A5 -> 问题摘要：采购管理内部控制执行不到位 | C4: ='3.采购管理'!A6 -> 1.部分采购项目未按规定执行询比价采购方式。 发展研究中心在2023至2025年度项目采购中，存在19个1万元（含）以上项目未执行询比价采购方式，直接确定供应商情况。其中：2023年涉及5个项目，采购金额 400,054.24 元；2024年涉及2个项目，采购金额81,770元；2025年涉及12个项目，采购金额 873,015元，其中，与北京国润新通酒店管理有限责任公司阳光国润分公司直接签订4笔，涉及金额224390元。 2.采购评审程序不规范，询比价评审依据缺失。 在2024至2025年6个项目询比价采购中，未见采购需求文件或询价通知书，未明确成交原则、判定规则，评审过程缺少客观依据。其中：2024年度3个项目，涉及金额176,995元，2025年度，采用询比价方式采购的3个项目，涉及金额141,000元。 3.采购项目验收环节不合规。一是2025年与国家市场监督管理总局专业技术人才开发中心签订的“市场监管总局网络学院北京分院运营项目”的项目委托合同，合同金额299,750元，于2025年12月15日由苏琦签字验收通过，验收小组人数不足，未按规定成立不少于2人的内部验收小组；二是个别项目未按规定履行验收程序。2023年3笔维修项目共计22,430元，凭证后未附验收确认单，具体包括：3月1# 凭证中央空调维修费9,800元、6月4#凭证空调维修费5,030元、6月5#凭证空调水循环系统维修费7,600元；2024年涉及3笔共计15,000元，具体包括：4月19#支付中诚安管理咨询有限公司评审服务费5,000元，未附验收确认单。 4.选取不具备相应资质的服务商购买预算评审服务。 2024年4月19#支付中诚安管理咨询有限公司预算评审服务费5000元，经查该供应商的营业范围为“财务咨询(不得开展审计,验资,查账,评估,代理记账等需要审批的业务,不得出具相应的审计报告,验资报告,查账报告,评估报告等文字材料)”，不具备出具预算评审报告的相应资质。 | D4: ='3.采购管理'!A12 -> 不符合《中华人民共和国政府采购法》第二十二条“供应商参加政府采购活动应当具备下列条件:（一）具有独立承担民事责任的能力；（二）具有良好的商业信誉和健全的财务会计制度”（三）具有履行合同所必需的设备和专业技术能力”第三十二条 “采购的货物规格、标准统一、现货货源充足且价格变化幅度小的政府采购项目，可以依照本法采用询价方式采购”《政府采购需求管理办法》（财库[2021]22号）第七条“采购需求应当明确采购标的需要实现的功能或目标，需满足的技术、商务要求”第十五条“采购需求应当作为确定采购项目、采购方式和采购文件编制的依据”《政府采购非招标采购方式管理办法》（财政部74号令）第十七条“询价通知书应当明确采购项目需求、供应商资格条件、报价要求、评定成交的标准等”《北京市市场监管发展研究中心采购管理办法》第二十四条“采购需求部门或归口管理部门应当成立不少于2人的验收小组，且采购执行与验收应当分离”《北京市财政预算评审管理实施细则》第十三条“财政部门开展财政预算评审时，可以委托有相关资质的中介机构、组织专家辅助工作的规定”的规定。 | E4: ='3.采购管理'!A8 -> 1.2023、2024年、2025年合同台账及合同。 2.《北京市市场监管发展研究中心采购管理办法》 3.2025年“市场监管总局网络学院北京分院运营项目”验收报告 4.2023年3月1#、6月4#、6月5#、2024年4月19#、11月16#。 5.2024年4月19#会计凭证及查询营业范围。
A5: 4 | B5: ='5.资产管理方面'!A5 -> 问题摘要：固定资产管理不严谨，存在账实不符问题 | C5: ='5.资产管理方面'!A6 -> 1.发展研究中心固定资产动态管理账实不符，部分资产使用信息不完整、不准确。 如：资产编号0430042025000001-0430042025000006、TY2023000001、TY2022000001-TY2021000014-TY2021000043等66件资产，包括碎纸机、台式机等原值合计364150元，与实际使用信息不符，未准确登记使用人、存放地点等使用信息。 2.存在闲置资产，未及时进行处置 如：资产编号TY2019000006-TY2019000024等37件资产，包括：终端接入设备、交换机等资产原值376,402元，现存放于标准化大厦，处于闲置状态，但固定资产动态库信息仍显示在用，与实际不符。 3.个别资产超标准配置。 如：资产编号TY2019000001，资产名称：复印机1台，规格型号：HP激光A3 X3A66A E72535DN ，入账价值73857元；资产编号TY2023000001，资产名称：摄像机及配件，1台，规格型号：索尼z190v，入账价值33,648元，超出规定标准。 4.固定资产盘点工作不够规范，基础信息登记不完整。 发展研究中心固定资产盘点表填写不规范，其中使用部门、存放地点等关键基础信息均填写为原单位部门，未根据中心实际资产使用、存放情况更新完善，导致盘点表无法真实反映固定资产当前实际使用状态、归属部门及存放位置，账实衔接不畅。 | D5: ='5.资产管理方面'!A12 -> 不符合《行政事业单位内部控制规范(试行)》第四十四条“单位应当加强对实物资产和无形资产的管理......(三）建立资产台账，加强资产的实物管理。单位应当定期清查盘点资产，确保账实相符。财会、资产管理、资产使用等部门或岗位应当定期对账，发现不符的，应当及时查明原因，并按照相关规定处理。(四)建立资产信息管理系统，做好资产的统计、报告、分析工作，实现对资产的动态管理””的规定。 不符合《行政事业单位办公设备配置标准表》（京财资产〔2019〕1128号附件）“复印机35000元/台、摄像机30000元/台”的规定。 | E5: ='5.资产管理方面'!A8 -> 1.2025年固定资产动态库台账、2.2025年固定资产盘点表
A6: 5 | B6: ='6.财务管理方面'!A5 -> 问题摘要：费用报销审批不严 | C6: ='6.财务管理方面'!A6 -> 2023年8月31日19#凭证列支购培训班饮用水费用3,000元，报销单据中科室负责人与领用人为翟静波同一人，审批与领用监督制约不到位，不相容岗位未有效分离。 | D6: ='6.财务管理方面'!A12 -> 不符合《会计基础工作规范》第四十八条“原始凭证的基本要求是：（一）原始凭证的内容必须具备：凭证的名称；填制凭证的日期；填制凭证单位名称或者填制人姓名；经办人员的签名或者盖章；接受凭证单位名称；经济业务内容；数量、单价和金额”的规定。 | E6: ='6.财务管理方面'!A8 -> 1.2023年8月31日19#
A7: 6 | B7: ='8.往来款挂账'!A5 -> 问题摘要：往来款项未及时清理 | C7: ='8.往来款挂账'!A6 -> 发展研究中心2025年末其他应收款存在长期挂账且无法收回的问题，挂账金额200000元，账龄已超过3年。该笔挂账资金系2013年6月、8月分两次支付给北京市工商行政管理局干部培训中心的借款，金额分别为150000元、50000元。经核查，北京市工商行政管理局干部培训中心已依据北京市编办京编办事[2014]97号文件批准，于2014年注销，导致该笔借款已无回收可能。发展研究中心分别于2016年7月7日向市局党组、2020年8月13日向市局科技与财务处提交了关于原市工商局干部培训中心借款请示，截至审计日，发展研究中心中心未对该笔无法收回的借款按规定计提坏账准备及进行核销处理。 | D7: ='8.往来款挂账'!A11 -> 不符合《政府会计制度》“1218其他应收款 四、事业单位应当于每年年末，对其他应收款进行全面检查，如发生不能收回的迹象，应当计提坏账准备。（一）对于账龄超过规定年限、确认无法收回的其他应收款，按照规定报经批准后予以核销。按照核销金额，借记“坏账准备”科目，贷记本科目。核销的其他应收款应当在备查簿中保留登记”《事业单位财务规则》“第五十条“事业单位应当对不同性质的负债分类管理，及时清理并按照规定办理结算，保证各项负债在规定期限内偿还”的规定。 | E7: ='8.往来款挂账'!A8 -> 2025年科目余额表、2023年科目余额表、北京市市场监管发展研究中心资产清查专项审计报告、北京市工商行政管理局干部学校关于处理原市工商局干部培训中心借款的请示。

Sheet 1.内部控制管理方面
A1: 审计工作底稿
A2: 被 审 计 单 位 名 称： | B2: 北京市市场监管发展研究中心 | E2: 编号：
A3: 审 计 项 目： | B3: 巡察财务审计 | C3: 审计人员： | D3: 卫俊芳 | E3: 日期： | F3: 46132 | G3: 第 页
A4: 会计期间及会计截止日： | B4: 2023年至2025年 | C4: 复核人员： | D4: 张雨寒金爱英 | E4: 日期： | F4: =F3+1 -> 46133 | G4: 共 页
A5: 问题摘要：内部控制体系文件不完整
A6: 1.内部控制体系文件不完整，未及时更新。发展研究中心内部控制手册尚处于修订完善阶段，未能提供最新完整、统一、现行有效的内部控制手册，不利于全面核查内控流程、岗位职责、风险防控等体系建设及执行情况，内部控制资料支撑不足。 2.内部控制制度体系不健全，制度缺失。 现有内控制度不完整，单位层面未建立内部控制风险评估、内部控制体系监督评价相关制度；业务层面缺少差旅费、会议费、会务卡管理等制度，内控覆盖不全面，难以有效开展风险防控、监督评价及经费规范管理。
A7: 取证清单：
A8: 《北京市市场监管发展研究中心财务制度汇编》
A9: 被审计单位就问题真实性及有关数据准确性的核实意见：
A10: 签字（盖章）：
A11: 审计人员意见：
A12: 不符合《行政事业单位内部控制规范》第七条 “单位应当根据本规范建立适合本单位实际情况的内部控制体系，并组织实施。具体工作包括梳理单位各类经济活动的业务流程，明确业务环节，系统分析经济活动风险，确定风险点，选择风险应对策略，在此基础上根据国家有关规定建立健全单位各项内部管理制度并督促相关工作人员认真执行”的规定。
A13: 一是加快内部控制手册修订工作，明确修订节点与完成时限，尽快形成完整、规范、统一、可执行的内控手册并正式印发执行；二是对现有内控制度进行全面梳理，及时制定完善内部控制风险评估、内部控制体系监督评价、差旅费、会议费、会务卡管理等缺失制度，补齐制度短板，确保经费管理有章可循。

Sheet 2.预算编报方面
A1: 审计工作底稿
A2: 被 审 计 单 位 名 称： | B2: 北京市市场监管发展研究中心 | E2: 编号：
A3: 审 计 项 目： | B3: 巡察财务审计 | C3: 审计人员： | D3: 卫俊芳 | E3: 日期： | F3: 46132 | G3: 第 页
A4: 会计期间及会计截止日： | B4: 2023年至2025年 | C4: 复核人员： | D4: 张雨寒金爱英 | E4: 日期： | F4: =F3+1 -> 46133 | G4: 共 页
A5: 问题摘要：政府采购预算编报不准确，导致预算执行率低
A6: 发展研究中心“系统干部培训经费”编报不严谨，预算编报以“全员在外550元”为标准编制，但实际执行过程中未按照该标准落实，编报依据与实际执行情况脱节，导致政府采购预算实际执行率较低，2023年、2024年、2025年政府采购预算执行率分别为39.85%、13.08%、31%。
A7: 取证清单：
A8: 2023年、2024年、2025年决算报表。
A9: 被审计单位就问题真实性及有关数据准确性的核实意见：
A10: 签字（盖章）：
A11: 审计人员意见：
A12: 不符合《事业单位财务规则》第十一条“事业单位应当严格执行批准的预算。预算执行中，国家对财政补助收入和财政专户管理资金的预算一般不予调剂，确需调剂的，由事业单位报主管部门审核后报财政部门调剂；其他资金确需调剂的，按照国家有关规定办理”的规定。
A13: 优化预算编报依据，结合中心年度工作任务、人员配置、实际履职场景等因素，开展全面调研测算，确保预算编报贴合实际需求。

Sheet 3.采购管理
A1: 审计工作底稿
A2: 被 审 计 单 位 名 称： | B2: 北京市市场监管发展研究中心 | E2: 编号：
A3: 审 计 项 目： | B3: 巡察财务审计 | C3: 审计人员： | D3: 卫俊芳 | E3: 日期： | F3: 46129 | G3: 第 页
A4: 会计期间及会计截止日： | B4: 2023年至2025年 | C4: 复核人员： | D4: 张雨寒金爱英 | E4: 日期： | F4: =F3+1 -> 46130 | G4: 共 页
A5: 问题摘要：采购管理内部控制执行不到位
A6: 1.部分采购项目未按规定执行询比价采购方式。 发展研究中心在2023至2025年度项目采购中，存在19个1万元（含）以上项目未执行询比价采购方式，直接确定供应商情况。其中：2023年涉及5个项目，采购金额 400,054.24 元；2024年涉及2个项目，采购金额81,770元；2025年涉及12个项目，采购金额 873,015元，其中，与北京国润新通酒店管理有限责任公司阳光国润分公司直接签订4笔，涉及金额224390元。 2.采购评审程序不规范，询比价评审依据缺失。 在2024至2025年6个项目询比价采购中，未见采购需求文件或询价通知书，未明确成交原则、判定规则，评审过程缺少客观依据。其中：2024年度3个项目，涉及金额176,995元，2025年度，采用询比价方式采购的3个项目，涉及金额141,000元。 3.采购项目验收环节不合规。一是2025年与国家市场监督管理总局专业技术人才开发中心签订的“市场监管总局网络学院北京分院运营项目”的项目委托合同，合同金额299,750元，于2025年12月15日由苏琦签字验收通过，验收小组人数不足，未按规定成立不少于2人的内部验收小组；二是个别项目未按规定履行验收程序。2023年3笔维修项目共计22,430元，凭证后未附验收确认单，具体包括：3月1# 凭证中央空调维修费9,800元、6月4#凭证空调维修费5,030元、6月5#凭证空调水循环系统维修费7,600元；2024年涉及3笔共计15,000元，具体包括：4月19#支付中诚安管理咨询有限公司评审服务费5,000元，未附验收确认单。 4.选取不具备相应资质的服务商购买预算评审服务。 2024年4月19#支付中诚安管理咨询有限公司预算评审服务费5000元，经查该供应商的营业范围为“财务咨询(不得开展审计,验资,查账,评估,代理记账等需要审批的业务,不得出具相应的审计报告,验资报告,查账报告,评估报告等文字材料)”，不具备出具预算评审报告的相应资质。
A7: 取证清单：
A8: 1.2023、2024年、2025年合同台账及合同。 2.《北京市市场监管发展研究中心采购管理办法》 3.2025年“市场监管总局网络学院北京分院运营项目”验收报告 4.2023年3月1#、6月4#、6月5#、2024年4月19#、11月16#。 5.2024年4月19#会计凭证及查询营业范围。
A9: 被审计单位就问题真实性及有关数据准确性的核实意见：
A10: 签字（盖章）：
A11: 审计人员意见：
A12: 不符合《中华人民共和国政府采购法》第二十二条“供应商参加政府采购活动应当具备下列条件:（一）具有独立承担民事责任的能力；（二）具有良好的商业信誉和健全的财务会计制度”（三）具有履行合同所必需的设备和专业技术能力”第三十二条 “采购的货物规格、标准统一、现货货源充足且价格变化幅度小的政府采购项目，可以依照本法采用询价方式采购”《政府采购需求管理办法》（财库[2021]22号）第七条“采购需求应当明确采购标的需要实现的功能或目标，需满足的技术、商务要求”第十五条“采购需求应当作为确定采购项目、采购方式和采购文件编制的依据”《政府采购非招标采购方式管理办法》（财政部74号令）第十七条“询价通知书应当明确采购项目需求、供应商资格条件、报价要求、评定成交的标准等”《北京市市场监管发展研究中心采购管理办法》第二十四条“采购需求部门或归口管理部门应当成立不少于2人的验收小组，且采购执行与验收应当分离”《北京市财政预算评审管理实施细则》第十三条“财政部门开展财政预算评审时，可以委托有相关资质的中介机构、组织专家辅助工作的规定”的规定。
A13: 修订政府采购管理办法，一是完善询比价采购管理相关内容，明确限额标准与采购方式适用情形，执行询比价程序；制定规范的询价通知书、采购需求模板，明确采购内容、技术要求、服务标准及评审流程；二是规范服务采购管理，在选取评审、咨询等专业服务机构时，认真核查供应商资质、执业资格及业务范围，确保服务商具备相应服务能力；三是规范服务采购管理，在选取评审、咨询等专业服务机构时，认真核查供应商资质、执业资格及业务范围，确保服务商具备相应服务能力

Sheet 4.采购管理执行S
A1: 审计工作底稿
A2: 被 审 计 单 位 名 称： | B2: 北京市市场监管发展研究中心 | E2: 编号：
A3: 审 计 项 目： | B3: 巡察财务审计 | C3: 审计人员： | D3: 卫俊芳 | E3: 日期： | F3: 46129 | G3: 第 页
A4: 会计期间及会计截止日： | B4: 2023年至2025年 | C4: 复核人员： | D4: 张雨寒金爱英 | E4: 日期： | F4: =F3+1 -> 46130 | G4: 共 页
A5: 问题摘要： | H5: 采购管理内部控制执行不到位
H6: 11月16#支付北京中普信华会计师事务所有限公司2笔共计10000元预算评审计费，未附验收确认单，且与北京中普信华会计师事务所有限公司签订两份评审业务合同，分别为《出版物印刷经费项目》和《国家市场监管总局网络学院北京分院运营服务项目》的评审业务，合同金额分别为5000元，可能存在拆分采购合同，未履行采购程序。
A7: 取证清单：
H8: 2023年11月16#。
A9: 被审计单位就问题真实性及有关数据准确性的核实意见：
A10: 签字（盖章）：
A11: 审计人员意见：

Sheet 5.资产管理方面
A1: 审计工作底稿
A2: 被 审 计 单 位 名 称： | B2: 北京市市场监管发展研究中心 | E2: 编号：
A3: 审 计 项 目： | B3: 巡察财务审计 | C3: 审计人员： | D3: 卫俊芳 | E3: 日期： | F3: 46128 | G3: 第 页
A4: 会计期间及会计截止日： | B4: 2023年至2025年 | C4: 复核人员： | D4: 张雨寒金爱英 | E4: 日期： | F4: =F3+1 -> 46129 | G4: 共 页
A5: 问题摘要：固定资产管理不严谨，存在账实不符问题
A6: 1.发展研究中心固定资产动态管理账实不符，部分资产使用信息不完整、不准确。 如：资产编号0430042025000001-0430042025000006、TY2023000001、TY2022000001-TY2021000014-TY2021000043等66件资产，包括碎纸机、台式机等原值合计364150元，与实际使用信息不符，未准确登记使用人、存放地点等使用信息。 2.存在闲置资产，未及时进行处置 如：资产编号TY2019000006-TY2019000024等37件资产，包括：终端接入设备、交换机等资产原值376,402元，现存放于标准化大厦，处于闲置状态，但固定资产动态库信息仍显示在用，与实际不符。 3.个别资产超标准配置。 如：资产编号TY2019000001，资产名称：复印机1台，规格型号：HP激光A3 X3A66A E72535DN ，入账价值73857元；资产编号TY2023000001，资产名称：摄像机及配件，1台，规格型号：索尼z190v，入账价值33,648元，超出规定标准。 4.固定资产盘点工作不够规范，基础信息登记不完整。 发展研究中心固定资产盘点表填写不规范，其中使用部门、存放地点等关键基础信息均填写为原单位部门，未根据中心实际资产使用、存放情况更新完善，导致盘点表无法真实反映固定资产当前实际使用状态、归属部门及存放位置，账实衔接不畅。
A7: 取证清单：
A8: 1.2025年固定资产动态库台账、2.2025年固定资产盘点表
A9: 被审计单位就问题真实性及有关数据准确性的核实意见：
A10: 签字（盖章）：
A11: 审计人员意见：
A12: 不符合《行政事业单位内部控制规范(试行)》第四十四条“单位应当加强对实物资产和无形资产的管理......(三）建立资产台账，加强资产的实物管理。单位应当定期清查盘点资产，确保账实相符。财会、资产管理、资产使用等部门或岗位应当定期对账，发现不符的，应当及时查明原因，并按照相关规定处理。(四)建立资产信息管理系统，做好资产的统计、报告、分析工作，实现对资产的动态管理””的规定。 不符合《行政事业单位办公设备配置标准表》（京财资产〔2019〕1128号附件）“复印机35000元/台、摄像机30000元/台”的规定。
A13: 完善资产动态信息和实物管理，明确资产编号、使用部门和管理部门责任，落实资产使用人在资产管理中的责任，保证资产清晰、完整，利于管理；对照实际资产使用情况，重新梳理固定资产信息，更正盘点表中使用部门、存放地点等错误信息，保证盘点表信息真实、完整、准确，实现账卡、账物、账账相符

Sheet 6.财务管理方面
A1: 审计工作底稿
A2: 被 审 计 单 位 名 称： | B2: 北京市市场监管发展研究中心 | E2: 编号：
A3: 审 计 项 目： | B3: 巡察财务审计 | C3: 审计人员： | D3: 卫俊芳 | E3: 日期： | F3: 46128 | G3: 第 页
A4: 会计期间及会计截止日： | B4: 2023年至2025年 | C4: 复核人员： | D4: 张雨寒金爱英 | E4: 日期： | F4: =F3+1 -> 46129 | G4: 共 页
A5: 问题摘要：费用报销审批不严
A6: 2023年8月31日19#凭证列支购培训班饮用水费用3,000元，报销单据中科室负责人与领用人为翟静波同一人，审批与领用监督制约不到位，不相容岗位未有效分离。
A7: 取证清单：
A8: 1.2023年8月31日19#
A9: 被审计单位就问题真实性及有关数据准确性的核实意见：
A10: 签字（盖章）：
A11: 审计人员意见：
A12: 不符合《会计基础工作规范》第四十八条“原始凭证的基本要求是：（一）原始凭证的内容必须具备：凭证的名称；填制凭证的日期；填制凭证单位名称或者填制人姓名；经办人员的签名或者盖章；接受凭证单位名称；经济业务内容；数量、单价和金额”的规定。
A13: 补充完善该笔讲课费报销资料，补齐授课人员职务任职文件、职称证书或单位出具的身份资质证明，附入凭证归档。

Sheet 7.财务管理方面 S
A1: 审计工作底稿 | K1: 9笔行政事业单位公职人员领取讲课费
A2: 被 审 计 单 位 名 称： | B2: 北京市市场监管发展研究中心 | E2: 编号： | J2: 序号 | K2: 记账凭证 | L2: 问题类型 | M2: 涉及金额（元） | N2: 问题描述
A3: 审 计 项 目： | B3: 巡察财务审计 | C3: 审计人员： | D3: 卫俊芳 | E3: 日期： | F3: 46128 | G3: 第 页 | J3: 1 | K3: 2023-3-3# | L3: 培训课时费支出手续不齐全。讲课人员授课内容属于职权范围内的事项，发放标准政策依据不足。 | M3: 1000 | N3: 支付2022年统计分析培训班，授课时间2022年12月7日，陈晨，北京市统计局法规处副处长，授课学时1课时，实发金额500元；赖伟臣，北京市统计局设计管理处副处长，授课学时1课时，实发金额500元。
A4: 会计期间及会计截止日： | B4: 2023年至2025年 | C4: 复核人员： | D4: 张雨寒金爱英 | E4: 日期： | F4: =F3+1 -> 46129 | G4: 共 页 | J4: 2 | K4: 2023-5-1# | L4: 培训课时费支出手续不齐全。讲课人员授课内容属于职权范围内的事项，发放标准政策依据不足。 | M4: 5000 | N4: 授课班次：2023年度食品安全检查员（生产领域）能力提升培训和抽查考试。2023年3月31日，曲传勇，国家市场总局食品生产司，二级调研员。实授课时4课时，实发金额2000元；李东卫，国家市场监管局网监司二级巡视员，实授课时3课时，实发金额3000元。
A5: 问题摘要： | H5: 费用报销审批不严 | J5: 3 | K5: 2023-9-2# | L5: 培训课时费支出手续不齐全。讲课人员授课内容属于职权范围内的事项，发放标准政策依据不足。 | M5: 2000 | N5: 授课班次：2023年第六期“市场监管大讲堂”。2023年8月8日，李育平，国家市场监管总局规划司发展规划处处长，实授课时4课时，实发金额2000元。
H6: 培训讲课费报销附件不完整，缺少授课人员资质证明材料（行政事业单位公职人员）。 2023年—2025年报销培训讲课费共计9笔、金额34,000元，报销凭证后均未附授课人员职称、职务任职文件、专业资质证书，发放标准依据不充分。 | J6: 4 | K6: 2023-12-9# | L6: 培训课时费支出手续不齐全。讲课人员授课内容属于职权范围内的事项，发放标准政策依据不足。 | M6: 14000 | N6: 支付2023年9月至11月份专业班次培训授课教师讲课费，其中涉及部分讲师未附证明信息材料，讲课人员来自上级单位且授课内容属于职权范围内的事项，涉及“不得因履行本职工作额外取酬” 如：授课班次”2023年依法行政工作骨千培训班”，2023年9月5日，吴苗林，市司法局法治调研处处长，实授课时4课时，实发金额2000元。 授课班次:“全面优化营商环境助力企业高质量发展”专题培训班，9月26日，郭建广，市场监管总局登记注册局二级调研员，实授课时4课时，实发金额2000元。 授课班次:2023年全市特殊食品生产企业培训会，10月31日，宛超，市场总局特食司保健食品注册处处长，实授课时4课时 ，实发金额2000元。 授课班次:2023年北京市打击侵权假冒工作业务培训班，10月17日，韩尊亮，市场监管总局执法稽查局二级调研员，实授课时4课时，实发金额2000元。 授课班次“2023年公平竞争审查网络培训会”，10月19日，林迈，国家市场监督管理总局竞争政策协调司公平竞争审查处三级调研员，实授课时4课时，实发金额2000元。 授课班次“2023年新闻宣传培训班”，11月22日，徐建广，北京市委宣传部副部长北京市人民政府新闻办公室主任、市人民政府新闻发言人，实授课时4课时，实发金额4000元。
A7: 取证清单： | J7: 5 | K7: 2023-12-34# | L7: 培训课时费支出手续不齐全。讲课人员授课内容属于职权范围内的事项，发放标准政策依据不足。 | M7: 2000 | N7: 市局第三期优秀年轻干部培训班培训费，9月14日14点至17点，案例教学：市场秩序类典型案例分析，张晶，国家市场监管总局执法稽查局执法监督处处长，实发金额2000元
H8: 2.2023-3-3#、2023-5-1#、2023-9-2#、2023-12-9#、2023-12-34#、2024-10-3#、2024-11-6#、2025-3-3#、2025-6-2# | J8: 6 | K8: 2024-10-3# | L8: 培训课时费支出手续不齐全。讲课人员授课内容属于职权范围内的事项，发放标准政策依据不足。 | M8: 4000 | N8: 授课班次：2024年第三期食品安全检查员（C类）培训，2024年8月13日，宋玉红，国家市场监管总局食品经营司综合处二级调研员，实授课时4课时，实发金额2000元； 授课班次：2024年北京市打击侵权假冒工作业务培训，2024年9月6日，曹祎宇，国家市场监督管理总局双打督查联络处副处长，实授课时4课时，实发金额2000元；
A9: 被审计单位就问题真实性及有关数据准确性的核实意见： | J9: 7 | K9: 2024-11-6# | L9: 培训课时费支出手续不齐全。讲课人员授课内容属于职权范围内的事项，发放标准政策依据不足。 | M9: 2000 | N9: 授课班次：市局2024年履职能力提升培训班培训费，11月4日9点30至12点，卢雁，国家市场监督管理总局发展研究中心部门主任、处长，实授课时4课时，实发金额2000元
A10: 签字（盖章）： | J10: 8 | K10: 2025-3-3# | L10: 培训课时费支出手续不齐全。讲课人员授课内容属于职权范围内的事项，发放标准政策依据不足。 | M10: 2000 | N10: 2025年2月19日，授课班次:《集贸市场计量监督管理办法》培训，郑华欣，市场监管总局计量司法制处处长，授课内容《集贸市场计量监督管理办法》，实授课时4课时，实发金额2000元。
A11: 审计人员意见： | J11: 9 | K11: 2025-6-2# | L11: 培训课时费支出手续不齐全。讲课人员授课内容属于职权范围内的事项，发放标准政策依据不足。 | M11: 2000 | N11: 2025年5月9日，授课班次:2025年第三期市场监管大讲堂，王琨，市场监管总局执法稽查局执法督查处副处长，授课内容《牢固树立监管为民理念纵深推进服务型执法》，实授课时4课时，实发金额2000元。
M12: 34000
A13: 补充完善该笔讲课费报销资料，补齐授课人员职务任职文件、职称证书或单位出具的身份资质证明，附入凭证归档。

Sheet 8.往来款挂账
A1: 审计工作底稿
A2: 被 审 计 单 位 名 称： | B2: 北京市市场监管发展研究中心 | E2: 编号：
A3: 审 计 项 目： | B3: 巡察财务审计 | C3: 审计人员： | D3: 卫俊芳 | E3: 日期： | F3: 46127 | G3: 第 页
A4: 会计期间及会计截止日： | B4: 2023年至2025年 | C4: 复核人员： | D4: 张雨寒金爱英 | E4: 日期： | F4: =F3+1 -> 46128 | G4: 共 页
A5: 问题摘要：往来款项未及时清理
A6: 发展研究中心2025年末其他应收款存在长期挂账且无法收回的问题，挂账金额200000元，账龄已超过3年。该笔挂账资金系2013年6月、8月分两次支付给北京市工商行政管理局干部培训中心的借款，金额分别为150000元、50000元。经核查，北京市工商行政管理局干部培训中心已依据北京市编办京编办事[2014]97号文件批准，于2014年注销，导致该笔借款已无回收可能。发展研究中心分别于2016年7月7日向市局党组、2020年8月13日向市局科技与财务处提交了关于原市工商局干部培训中心借款请示，截至审计日，发展研究中心中心未对该笔无法收回的借款按规定计提坏账准备及进行核销处理。
A7: 取证清单：
A8: 2025年科目余额表、2023年科目余额表、北京市市场监管发展研究中心资产清查专项审计报告、北京市工商行政管理局干部学校关于处理原市工商局干部培训中心借款的请示。
A9: 签字（盖章）：
A10: 审计人员意见：
A11: 不符合《政府会计制度》“1218其他应收款 四、事业单位应当于每年年末，对其他应收款进行全面检查，如发生不能收回的迹象，应当计提坏账准备。（一）对于账龄超过规定年限、确认无法收回的其他应收款，按照规定报经批准后予以核销。按照核销金额，借记“坏账准备”科目，贷记本科目。核销的其他应收款应当在备查簿中保留登记”《事业单位财务规则》“第五十条“事业单位应当对不同性质的负债分类管理，及时清理并按照规定办理结算，保证各项负债在规定期限内偿还”的规定。
A12: 建议结合前期已上报的请示材料，尽快向主管部门履行资产损失核销报批流程，待批复后及时完成账务核销处理，消化历史遗留往来挂账问题。

Sheet 9.库存酒水清理S
A1: 审计工作底稿
A2: 被 审 计 单 位 名 称： | B2: 北京市市场监管发展研究中心 | E2: 编号：
A3: 审 计 项 目： | B3: 巡察财务审计 | C3: 审计人员： | D3: 卫俊芳 | E3: 日期： | F3: 46128 | G3: 第 页
A4: 会计期间及会计截止日： | B4: 2023年至2025年 | C4: 复核人员： | D4: 张雨寒金爱英 | E4: 日期： | F4: =F3+1 -> 46129 | G4: 共 页
A5: 问题摘要： | H5: 历史遗留库存酒水仍未清理处置完成
H6: 发展研究中心由于历史原因形成库存酒水共251瓶，价值92,920元。于2023年11月委托北京产权交易所对封存酒水进行评估、拍卖、回收，并将实物移交北京产权交易所。由于部分酒水因防伪标识存疑或过期等原因无法拍卖需销毁处理，于2024年7月22日向北京产权交易所有限公司发出《关于委托物资环保销毁的函》，请北京产权交易所有限公司对72瓶代做环保销毁处理；北京产权交易所有限公司于2024年7月22日已拍卖成功132瓶。剩余47瓶，经宏米平字[2024]第PX027号评估报告中确认评估价值1360元，于2024年11月20日，重新开展公开拍卖工作。但截至审计日，上述酒水拍卖处置工作仍在推进中，未处置完毕。
A7: 取证清单：
H8: 1.关于酒水拍卖进展情况说明；2.拍卖酒水函；3.委托函；4.销毁明细表；5.资产明细表
A9: 被审计单位就问题真实性及有关数据准确性的核实意见：
A10: 签字（盖章）：
A11: 审计人员意见：

Sheet 10.会计基础工作S
A1: 审计工作底稿
A2: 被 审 计 单 位 名 称： | B2: 北京市市场监管发展研究中心 | E2: 编号：
A3: 审 计 项 目： | B3: 巡察财务审计 | C3: 审计人员： | D3: 卫俊芳 | E3: 日期： | F3: 46128 | G3: 第 页
A4: 会计期间及会计截止日： | B4: 2023年至2025年 | C4: 复核人员： | D4: 张雨寒金爱英 | E4: 日期： | F4: =F3+1 -> 46129 | G4: 共 页
A5: 问题摘要： | H5: 会计基础工作不规范位，存在凭证附件不全、档案未及时归档问题
H6: 1.会计凭证附件资料不完整，原始依据不充分。 （1）固定资产入账原始资料缺失 2025年7月31日财20# 凭证记载，购入设备类固定资产入账金额24577元，该笔固定资产在办理入账核算时，仅直接进行账务处理，记账凭证后未附资产名称、规格型号、数量等相关资产信息资料，入账依据不完整。 （2）计提折旧未附原始依据 2025年1-12月计提固定资产折旧12笔，共98515.74元，凭证后无均未附折旧计算表、折旧清单等原始依据，仅直接进行账务处理，会计凭证附件不完整，无法完整反映折旧计算过程及依据。 3.会计档案未按规定及时整理装订归档。 截至审计日，发展研究中心2025年度会计凭证未完成装订及归档工作。
A7: 取证清单：
H8: 1.2025年7月31日20#会计凭证 2.2025年1月13#、2月3#、3月27#、4月27#、5月19#、6月23#、7月21#、8月19#、9月31#、10月19#、11月24#、12月36#会计凭证 3.2025年度会计凭证。
A9: 被审计单位就问题真实性及有关数据准确性的核实意见：
A10: 签字（盖章）：
A11: 审计人员意见：
